{
  "Top": "led",
  "RtlTop": "led",
  "RtlPrefix": "",
  "SourceLanguage": "cpp",
  "ResetStyle": "control",
  "GenerateBdFiles": "0",
  "HostMachineBits": "64",
  "Target": {
    "Family": "zynq",
    "Device": "xc7z020",
    "Package": "clg400",
    "Speed": "-2"
  },
  "HlsSolution": {
    
  },
  "ClockInfo": {
    "ClockName": "ap_clk",
    "ClockPeriod": "10",
    "IsCombLogic": "0",
    "II": "x",
    "Latency": "50000001",
    "Uncertainty": "1.25"
  },
  "Xdc": {"OocClocks": ["create_clock -name ap_clk -period 10.000 [get_ports ap_clk]"]},
  "Ipx": {
    "Vendor": "xilinx.com",
    "Library": "hls",
    "Name": "led",
    "Version": "1.0",
    "DisplayName": "Led",
    "Revision": "",
    "Description": "An IP generated by Vivado HLS",
    "Taxonomy": "\/VIVADO_HLS_IP",
    "AutoFamilySupport": ""
  },
  "Files": {
    "CSource": ["..\/led.cpp"],
    "Vhdl": ["impl\/vhdl\/led.vhd"],
    "Verilog": ["impl\/verilog\/led.v"],
    "Misc": ["impl\/misc\/logo.png"],
    "DesignXml": "D:\/MyWorkSpace\/ZYNQ\/HLS\/led\/led\/solution1\/.autopilot\/db\/led.design.xml"
  },
  "SubcoreInfo": {
    "HasXpmMemory": false,
    "HasClockedDsp": false,
    "IP": []
  },
  "Interfaces": {
    "ap_clk": {
      "type": "clock",
      "ctype": {"CLK": {"Type": "bool"}},
      "reset": "ap_rst"
    },
    "ap_rst": {
      "type": "reset",
      "polarity": "ACTIVE_HIGH",
      "ctype": {"RST": {"Type": "bool"}}
    },
    "led_V": {
      "type": "data",
      "dir": "out",
      "width": "1",
      "ctype": {"DATA": {
          "Type": "integer signed",
          "Width": "1"
        }}
    }
  },
  "RtlPorts": {
    "ap_clk": {
      "dir": "in",
      "width": "1"
    },
    "ap_rst": {
      "dir": "in",
      "width": "1"
    },
    "led_V": {
      "dir": "out",
      "width": "1",
      "isVector": "true"
    }
  },
  "CPorts": {"led_V": {
      "interfaceRef": "led_V",
      "dir": "out",
      "dataWidth": "1",
      "handshakeRef": "ap_none",
      "firstOutLatency": "1"
    }},
  "ModuleInfo": {
    "Hierarchy": {"ModuleName": "led"},
    "Metrics": {"led": {
        "Latency": {
          "LatencyBest": "50000001",
          "LatencyAvg": "50000001",
          "LatencyWorst": "50000001",
          "PipelineII": "50000002",
          "PipelineDepth": "",
          "PipelineType": "none"
        },
        "Timing": {
          "Target": "10.00",
          "Uncertainty": "1.25",
          "Estimate": "1.988"
        },
        "Loops": [{
            "Name": "Loop 1",
            "TripCount": "50000000",
            "Latency": "50000000",
            "PipelineII": "",
            "PipelineDepth": "1"
          }],
        "Area": {
          "FF": "28",
          "LUT": "43",
          "BRAM_18K": "0",
          "DSP48E": "0"
        }
      }}
  },
  "Sdx": {
    "Target": "none",
    "ProfileOption": "0",
    "ProfileType": "none",
    "XO": "",
    "KernelName": "led",
    "EnableXoSwEmu": "1"
  },
  "GenData": {
    "DataVersion": "0.1",
    "Time": "2020-07-08 22:09:51 +0800",
    "ToolName": "vivado_hls",
    "ToolVersion": "2018.3"
  }
}
